ryan_mcp_weather_server/__init__.py
ryan_mcp_weather_server/server.py
ryan_mcp_weather_server-0.1.4.dist-info/METADATA
ryan_mcp_weather_server-0.1.4.dist-info/WHEEL
ryan_mcp_weather_server-0.1.4.dist-info/entry_points.txt
ryan_mcp_weather_server-0.1.4.dist-info/top_level.txt
ryan_mcp_weather_server-0.1.4.dist-info/RECORD
