Metadata-Version: 2.4
Name: ryan-mcp-weather-server
Version: 0.1.4
Summary: The MCP weather server
Author-email: Ryan Zheng <zhengjianhong95@gmail.com>
Keywords: mcp,weather
Requires-Python: >=3.13
Requires-Dist: httpx
Requires-Dist: mcp>=1.0.0
